elglib/LICENSE
elglib/MANIFEST.in
elglib/__init__.py
elglib/core.py
elglib/setup.py
elglib/utils.py
elglib/engine/LICENSE
elglib/engine/elg/calculate.upp
elglib/engine/elg/dickappa.upp
elglib/engine/elg/init.upp
elglib/engine/graphs/Alphabet.txt
elglib/engine/graphs/Norm.txt
elglib/engine/graphs/Sentence.fst2
elglib/engine/graphs/build/.gitkeep
elglib/engine/graphs/build/DicTaggerLemmas.fst2
elglib/engine/graphs/build/LICENSE
elglib/engine/platform/linux-i686/.gitkeep
elglib/engine/platform/linux-x86_64/.gitkeep
elglib/engine/platform/linux-x86_64/elg-unitex
elglib/engine/platform/osx/.gitkeep
elglib/engine/platform/win32/.gitkeep
elglib/engine/platform/win64/.gitkeep
elglib/tests/init.py
elglib/tests/test_core.py
parscival/__init__.py
parscival/version.ini
parscival/worker.py
parscival/schemas/__init__.py
parscival/schemas/3/engine-next.yaml
parscival/schemas/3/engine.yaml
parscival/utils/__init__.py
parscival/utils/logging.py
parscival/utils/version.py
parscival-0.11.0.dist-info/licenses/LICENSE.txt
parscival_plugins/__init__.py
parscival_plugins/curating.py
parscival_plugins/ingesting.py
parscival_plugins/initializing.py
parscival_plugins/mapping.py
parscival_plugins/parsing.py
parscival_plugins/storing.py
parscival_plugins/curating/deduplicate/hash_key_deduplicator.py
parscival_plugins/curating/encode/convert.py
parscival_plugins/curating/encode/time_granularity.py
parscival_plugins/curating/match/elg/elg_node_matcher.py
parscival_plugins/ingesting/__init__.py
parscival_plugins/ingesting/convert/__init__.py
parscival_plugins/ingesting/filter/__init__.py
parscival_plugins/initializing/__init__.py
parscival_plugins/initializing/validate/__init__.py
parscival_plugins/initializing/validate/dogma/__init__.py
parscival_plugins/initializing/validate/dogma/dogma.py
parscival_plugins/mapping/transform/data_ranker.py
parscival_plugins/mapping/transform/date_format.py
parscival_plugins/mapping/transform/regex_format.py
parscival_plugins/mapping/transform/regex_match_filter.py
parscival-0.11.0.dist-info/METADATA
parscival-0.11.0.dist-info/WHEEL
parscival-0.11.0.dist-info/entry_points.txt
parscival-0.11.0.dist-info/top_level.txt
parscival-0.11.0.dist-info/RECORD
