Metadata-Version: 2.4
Name: parscival
Version: 0.11.0
Summary: modular framework for ingesting, parsing, mapping, curating, validating and storing heterogeneous textual data
Home-page: https://gitlab.com/cortext/cortext-methods/parscival
Author: Cristian Martinez, Lionel Villard, Philippe Breucker
Author-email: nobody@nowhere.com
License: MIT
Project-URL: Source, https://gitlab.com/cortext/cortext-methods/parscival
Platform: Linux
Classifier: Development Status :: 4 - Beta
Classifier: Programming Language :: Python
Requires-Python: >=3.9
License-File: LICENSE.txt
Requires-Dist: importlib-metadata==4.11.3; python_version < "3.8"
Requires-Dist: cython
Requires-Dist: wheel
Requires-Dist: rich==10.16.1
Requires-Dist: parsimonious==0.10.0
Requires-Dist: pyyaml
Requires-Dist: klepto==0.2.1
Requires-Dist: h5py==3.11.0
Requires-Dist: jinja2==3.0.3
Requires-Dist: pysqlite3==0.5.2
Requires-Dist: pluginlib==0.9.0
Requires-Dist: python-dotenv==0.20.0
Requires-Dist: python-dateutil==2.8.2
Requires-Dist: pyquery==2.0.0
Requires-Dist: semver==3.0.2
Requires-Dist: chardet==5.2.0
Requires-Dist: psutil==5.9.8
Requires-Dist: pandas==2.2.2
Requires-Dist: cerberus==1.3.5
Requires-Dist: python-box~=7.0
Requires-Dist: deepdiff~=7.0
Provides-Extra: testing
Requires-Dist: setuptools; extra == "testing"
Requires-Dist: pytest; extra == "testing"
Requires-Dist: pytest-cov; extra == "testing"
Dynamic: license-file
